{"CA": 481, "NY": 244, "MA": 174, "WA": 151, "TX": 135, "DC": 105, "WI": 93, "ME": 78, "CO": 69, "NJ": 69, "OR": 65, "FL": 63, "PA": 61, "NC": 51, "AZ": 51, "VA": 49, "MI": 47, "OH": 44, "MN": 44, "IL": 43, "MO": 40, "HI": 34, "IN": 32, "GA": 31, "ID": 29, "MD": 29, "UT": 29, "CT": 26, "IA": 24, "KS": 21, "VT": 19, "RI": 19, "NM": 18, "NH": 18, "AR": 17, "TN": 16, "NE": 16, "OK": 14, "KY": 14, "NV": 13, "LA": 12, "SC": 12, "AL": 11, "MT": 10, "AK": 9, "WY": 8, "MS": 6, "ND": 6, "SD": 6, "WV": 6, "DE": 5, "GU": 1, "PR": 1}